MANIFEST.in
README.rst
setup.py
django_mstats/__init__.py
django_mstats/decorators.py
django_mstats/models.py
django_mstats/urls.py
django_mstats/views.py
django_mstats.egg-info/PKG-INFO
django_mstats.egg-info/SOURCES.txt
django_mstats.egg-info/dependency_links.txt
django_mstats.egg-info/not-zip-safe
django_mstats.egg-info/requires.txt
django_mstats.egg-info/top_level.txt
django_mstats/static/Chart.min.js
django_mstats/templates/mstats/base.html
django_mstats/templates/mstats/overview.html
django_mstats/templates/mstats/stats.html