Metadata-Version: 1.1
Name: django-mstats
Version: 0.1.1
Summary: Simple, re-usable, stateless Django app for visualizing and browsing statistics, mainly based on your existing Django models.
Home-page: https://github.com/heyman/django-mstats
Author: Jonatan Heyman
Author-email: jonatan@heyman.info
License: BSD
Download-URL: https://pypi.python.org/pypi/django-mstats
Platform: UNKNOWN
Classifier: Development Status :: 3 - Alpha
Classifier: Environment :: Web Environment
Classifier: Framework :: Django
Classifier: Intended Audience :: Developers
Classifier: License :: OSI Approved :: BSD License
Classifier: Operating System :: OS Independent
Classifier: Programming Language :: Python
Classifier: Programming Language :: Python :: 2
Classifier: Programming Language :: Python :: 2.6
Classifier: Programming Language :: Python :: 2.7
Classifier: Topic :: Software Development :: Libraries :: Python Modules
